abstractintelligence/__init__.py
abstractintelligence-0.1.0.dist-info/METADATA
abstractintelligence-0.1.0.dist-info/WHEEL
abstractintelligence-0.1.0.dist-info/top_level.txt
abstractintelligence-0.1.0.dist-info/RECORD
