Metadata-Version: 2.4
Name: abstractintelligence
Version: 0.1.0
Summary: A proactive Generative AI system built upon AbstractCore
Author-email: Laurent-Philippe albou <contact@example.com>
License: TBD
Project-URL: Homepage, https://github.com/lpalbou/AbstractIntelligence
Project-URL: Repository, https://github.com/lpalbou/AbstractIntelligence
Project-URL: Documentation, https://github.com/lpalbou/AbstractIntelligence/docs
Project-URL: Bug Tracker, https://github.com/lpalbou/AbstractIntelligence/issues
Classifier: Development Status :: 2 - Pre-Alpha
Classifier: Intended Audience :: Developers
Classifier: Intended Audience :: Science/Research
Classifier: Programming Language :: Python :: 3
Classifier: Programming Language :: Python :: 3.8
Classifier: Programming Language :: Python :: 3.9
Classifier: Programming Language :: Python :: 3.10
Classifier: Programming Language :: Python :: 3.11
Classifier: Programming Language :: Python :: 3.12
Classifier: Topic :: Scientific/Engineering :: Artificial Intelligence
Classifier: Topic :: Software Development :: Libraries :: Python Modules
Requires-Python: >=3.8
Provides-Extra: dev
Requires-Dist: pytest>=6.0; extra == "dev"
Requires-Dist: pytest-cov>=2.0; extra == "dev"
Requires-Dist: black>=21.0; extra == "dev"
Requires-Dist: isort>=5.0; extra == "dev"
Requires-Dist: flake8>=3.8; extra == "dev"
Requires-Dist: mypy>=0.900; extra == "dev"
